moly/__init__.py
moly/_version.py
moly/advanced/cubeprop.py
moly/advanced/__pycache__/cubeprop.cpython-37.pyc.140086153195216
moly/data/README.md
moly/data/__init__.py
moly/data/data_molecules.py
moly/data/timer.dat
moly/data/__pycache__/data_molecules.cpython-37.pyc.140001521454224
moly/data/__pycache__/data_molecules.cpython-37.pyc.140086152485024
moly/figure/__init__.py
moly/figure/colors.py
moly/figure/figure.py
moly/figure/layouts.py
moly/figure/subplot.py
moly/figure/widgets.py
moly/figure/__pycache__/figure.cpython-37.pyc.139865924754576
moly/figure/__pycache__/figure.cpython-37.pyc.140518096333968
moly/figure/__pycache__/figure.cpython-37.pyc.140576531856528
moly/figure/__pycache__/widgets.cpython-37.pyc.140001522440640
moly/figure/__pycache__/widgets.cpython-37.pyc.140086153192912
moly/layers/__init__.py
moly/layers/bonds.py
moly/layers/cube.py
moly/layers/geometry.py
moly/layers/measurements.py
moly/molecule/__init__.py
moly/molecule/shapes.py
moly/molecule/__pycache__/shapes.cpython-37.pyc.140086153151808
moly/psi4/points.py
moly/psi4/psi4.py
moly/psi4/.ipynb_checkpoints/points-checkpoint.py
moly/tests/Da.cube
moly/tests/Dt.cube
moly/tests/__init__.py
moly/tests/test_figure.py
moly/tests/test_moly.py
moly/tests/timer.dat
moly/tests/water.xyz
moly/tests/.ipynb_checkpoints/test_figure-checkpoint.py
moly-0.2.1.dist-info/LICENSE
moly-0.2.1.dist-info/METADATA
moly-0.2.1.dist-info/WHEEL
moly-0.2.1.dist-info/top_level.txt
moly-0.2.1.dist-info/RECORD
