Metadata-Version: 2.1
Name: moly
Version: 0.2.1
Summary: UNKNOWN
Home-page: UNKNOWN
Author: VH Chavez
Author-email: gonza445@purdue.edu
License: BSD-3-Clause
Platform: UNKNOWN
Requires-Dist: numpy
Requires-Dist: qcelemental
Requires-Dist: plotly (>=4.0.0)
